{
  "projects": [
    {
      "name": "pasapalabra",
      "content": [
        {
          "type": "title",
          "level": 1,
          "content": "Pasapalabra"
        },
        {
          "type": "image",
          "sizeType": "wide", 
          "src": "pasaPalabra.png"
        }
      ]
    },
    {
      "name": "geogrid",
      "content":[
        {
          "type": "title",
          "level": 1,
          "content": "Geo Grid"
        },
        {
          "type": "image",
          "sizeType": "long", 
          "src": "geoGrid.png"
        }
      ]
    },
    {
      "name": "tictactoe",
      "content":[
        {
          "type": "title",
          "level": 1,
          "content": "Tic Tac Toe"
        },
        {
          "type": "image",
          "sizeType": "long", 
          "src": "tictactoe.png"
        }
      ]
    }
  ]
}